vampireformac/PCA.py
vampireformac/UI_generator.py
vampireformac/__init__.py
vampireformac/bd_resample.py
vampireformac/bdreg.py
vampireformac/clusterSM.py
vampireformac/command_execute.py
vampireformac/command_sort.py
vampireformac/conv.py
vampireformac/fspecial.py
vampireformac/get_bdprops_v3b.py
vampireformac/get_curvature2.py
vampireformac/get_shape.py
vampireformac/ginicoeff.py
vampireformac/harmmean.py
vampireformac/interface.py
vampireformac/main.py
vampireformac/mask_reader_individual.py
vampireformac/mask_remover.py
vampireformac/mask_simplifier.py
vampireformac/maskreader.py
vampireformac/maskreader_new.py
vampireformac/masksort.py
vampireformac/mode.py
vampireformac/pca_bdreg.py
vampireformac/polyfitw.py
vampireformac/reg_bd3.py
vampireformac/reg_bd_svd.py
vampireformac/test.py
vampireformac-0.0.9.data/scripts/interface-run.py
vampireformac-0.0.9.dist-info/METADATA
vampireformac-0.0.9.dist-info/RECORD
vampireformac-0.0.9.dist-info/WHEEL
vampireformac-0.0.9.dist-info/top_level.txt
